simple_commands_model/__init__.py
simple_commands_model/image_process/process_image.py
simple_commands_model/tf/cnn.py
simple_commands_model-0.0.1.dist-info/LICENSE
simple_commands_model-0.0.1.dist-info/METADATA
simple_commands_model-0.0.1.dist-info/WHEEL
simple_commands_model-0.0.1.dist-info/top_level.txt
simple_commands_model-0.0.1.dist-info/RECORD
